hackernews/__init__.py
hackernews/settings.py
tests/__init__.py
tests/test_api_version.py
tests/test_ask_stories.py
tests/test_get_all.py
tests/test_get_async.py
tests/test_get_item.py
tests/test_get_items_by_ids.py
tests/test_get_last.py
tests/test_get_max_item.py
tests/test_get_sync.py
tests/test_get_user.py
tests/test_get_users_by_ids.py
tests/test_job_stories.py
tests/test_new_stories.py
tests/test_show_stories.py
tests/test_top_stories.py
tests/test_updates.py
haxor-1.2.4.dist-info/LICENSE
haxor-1.2.4.dist-info/METADATA
haxor-1.2.4.dist-info/WHEEL
haxor-1.2.4.dist-info/top_level.txt
haxor-1.2.4.dist-info/RECORD
