Metadata-Version: 2.1
Name: haxor
Version: 1.2.4
Summary: Unofficial Python wrapper for Hacker News API
Home-page: https://github.com/avinassh/haxor/
Author: Avinash Sajjanshetty
Author-email: a@sajjanshetty.com
License: MIT
Classifier: Development Status :: 3 - Alpha
Classifier: License :: OSI Approved :: MIT License
Classifier: Operating System :: POSIX
Classifier: Intended Audience :: Developers
Classifier: Natural Language :: English
Classifier: Operating System :: OS Independent
Classifier: Programming Language :: Python
Classifier: Programming Language :: Python :: 3.6
Classifier: Topic :: Internet
Classifier: Topic :: Software Development :: Libraries
Classifier: Topic :: Software Development :: Libraries :: Python Modules
Classifier: Topic :: Utilities
License-File: LICENSE
Requires-Dist: aiohttp ==3.9.1
Requires-Dist: requests >=2.21.0
